designs/rtl/sar_logic/sar_logic.v
module sar_logic #(
    parameter N = 8
)(
    input  wire         clk,
    input  wire         rst_n,
    input  wire         start,
    output reg          eoc,
    output reg          busy,
    input  wire         comp_out,
    output reg [N-1:0]  dac_out,
    output reg [N-1:0]  dout,
    output reg          dout_valid
);

localparam IDLE    = 2'd0;
localparam SAMPLE  = 2'd1;
localparam CONVERT = 2'd2;
localparam DONE    = 2'd3;

localparam IDX_W = $clog2(N);
localparam [31:0]      MSB_FULL = N - 1;
localparam [IDX_W-1:0] MSB_IDX  = MSB_FULL[IDX_W-1:0];   // index of the most-significant bit

reg [1:0]          state;
reg [IDX_W-1:0]    bit_idx;
reg [N-1:0]        sar_reg;

always @(posedge clk or negedge rst_n) begin
    if (!rst_n) begin
        state      <= IDLE;
        dac_out    <= {N{1'b0}};
        dout       <= {N{1'b0}};
        dout_valid <= 1'b0;
        busy       <= 1'b0;
        eoc        <= 1'b0;
        bit_idx    <= MSB_IDX;
        sar_reg    <= {N{1'b0}};
    end
    else begin
        dout_valid <= 1'b0;
        eoc        <= 1'b0;

        case (state)

            IDLE: begin
                busy <= 1'b0;
                if (start) begin
                    state   <= SAMPLE;
                    busy    <= 1'b1;
                    bit_idx <= MSB_IDX;
                    sar_reg <= {N{1'b0}};
                end
            end

            SAMPLE: begin
                state   <= CONVERT;
                dac_out <= ({{N-1{1'b0}}, 1'b1} << (N-1));
            end

            CONVERT: begin
                // Capture comparator result for current bit
                if (comp_out)
                    sar_reg <= sar_reg | ({{N-1{1'b0}}, 1'b1} << bit_idx);

                if (bit_idx == 0) begin
                    state   <= DONE;
                    // update dac_out on the final bit too
                    dac_out <= sar_reg | ({{N-1{1'b0}}, comp_out} << bit_idx);
                end
                else begin
                    bit_idx <= bit_idx - 1'b1;
                    dac_out <= (sar_reg | ({{N-1{1'b0}}, comp_out} << bit_idx))
                             | ({{N-1{1'b0}}, 1'b1} << (bit_idx - 1'b1));
                end
            end

            DONE: begin
                dout       <= sar_reg;
                dout_valid <= 1'b1;
                eoc        <= 1'b1;
                busy       <= 1'b0;
                state      <= IDLE;
            end

        endcase
    end
end

endmodule

designs/rtl/sar_logic/tb_sar_logic.v
`timescale 1ns/1ps

module tb_sar_logic;
    parameter N = 8;

    // Testbench signals
    reg            clk;
    reg            rst_n;
    reg            start;
    reg            comp_out;
    wire [N-1:0]   dac_out;
    wire [N-1:0]   dout;
    wire           dout_valid;
    wire           busy;
    wire           eoc;

    // Internal testbench variables
    reg  [N-1:0]   Vin;
    integer        errors;

    // Instantiate DUT
    sar_logic #(.N(N)) dut (
        .clk(clk),
        .rst_n(rst_n),
        .start(start),
        .comp_out(comp_out),
        .dac_out(dac_out),
        .dout(dout),
        .dout_valid(dout_valid),
        .busy(busy),
        .eoc(eoc)
    );

    // Clock generation: 10ns period (100 MHz)
    initial begin
        clk = 0;
        forever #5 clk = ~clk;
    end

    // Mock Comparator: compares DAC output against the analog input (Vin)
    always @(*) begin
        comp_out = (dac_out <= Vin);
    end

    // VCD Dump for GTKWave
    initial begin
        $dumpfile("sar_sim.vcd");
        $dumpvars(0, tb_sar_logic);
    end

    // Watchdog Timer (prevents simulation from hanging if 'eoc' never asserts)
    initial begin
        #5000;
        $display("\n[FATAL ERROR] Simulation Timeout! EOC never asserted.");
        $finish;
    end

    // Reusable task to test a specific voltage value
    task test_voltage;
        input [N-1:0] test_val;
        begin
            Vin = test_val;
            
            // Trigger conversion
            @(posedge clk);
            start = 1;
            @(posedge clk);
            start = 0;

            // Wait for End of Conversion
            wait(eoc);
            
            // Check results on the next clock cycle when dout_valid should be high
            @(posedge clk);
            if (dout === Vin && dout_valid === 1'b1) begin
                $display("[PASS] Vin = %3d (0x%h) | ADC out = %3d", Vin, Vin, dout);
            end else begin
                $display("[FAIL] Vin = %3d (0x%h) | Expected = %3d, Got = %3d, Valid = %b", 
                         Vin, Vin, Vin, dout, dout_valid);
                errors = errors + 1;
            end
            
            // Small delay between conversions
            #20;
        end
    endtask

    // Main Stimulus Sequence
    initial begin
        // Initialize
        rst_n = 0;
        start = 0;
        Vin   = 0;
        errors = 0;

        // Apply Reset
        #20;
        rst_n = 1;
        #20;

        $display("========================================");
        $display("   Starting SAR ADC Testbench   ");
        $display("========================================");

        // Test Case 1: Mid-scale
        test_voltage(8'd128);

        // Test Case 2: User's original test
        test_voltage(8'hA5);

        // Test Case 3: Zero scale (Edge Case)
        test_voltage(8'd0);

        // Test Case 4: Full scale (Edge Case)
        test_voltage(8'd255);

        // Test Case 5: Random values
        test_voltage(8'd42);
        test_voltage(8'd199);
        test_voltage(8'd7);

        // Final Report
        $display("========================================");
        if (errors == 0)
            $display("   SIMULATION PASSED! (0 Errors)   ");
        else
            $display("   SIMULATION FAILED! (%0d Errors)   ", errors);
        $display("========================================");
        
        $finish;
    end
endmodule

designs/rtl/sar_logic/sar_sim.vcd
$date
	Sun Jul  5 21:03:33 2026
$end
$version
	Icarus Verilog
$end
$timescale
	1ps
$end
$scope module tb_sar_logic $end
$var wire 1 ! eoc $end
$var wire 1 " dout_valid $end
$var wire 10 # dout [9:0] $end
$var wire 10 $ dac_out [9:0] $end
$var wire 1 % busy $end
$var parameter 32 & N $end
$var reg 10 ' Vin [9:0] $end
$var reg 1 ( clk $end
$var reg 1 ) comp_out $end
$var reg 1 * rst_n $end
$var reg 1 + start $end
$var integer 32 , errors [31:0] $end
$scope module dut $end
$var wire 1 ( clk $end
$var wire 1 ) comp_out $end
$var wire 1 * rst_n $end
$var wire 1 + start $end
$var parameter 2 - CONVERT $end
$var parameter 2 . DONE $end
$var parameter 2 / IDLE $end
$var parameter 32 0 IDX_W $end
$var parameter 32 1 MSB_FULL $end
$var parameter 4 2 MSB_IDX $end
$var parameter 32 3 N $end
$var parameter 2 4 SAMPLE $end
$var reg 4 5 bit_idx [3:0] $end
$var reg 1 % busy $end
$var reg 10 6 dac_out [9:0] $end
$var reg 10 7 dout [9:0] $end
$var reg 1 " dout_valid $end
$var reg 1 ! eoc $end
$var reg 10 8 sar_reg [9:0] $end
$var reg 2 9 state [1:0] $end
$upscope $end
$scope task test_voltage $end
$var reg 10 : test_val [9:0] $end
$upscope $end
$upscope $end
$enddefinitions $end
$comment Show the parameter values. $end
$dumpall
b1 4
b1010 3
b1001 2
b1001 1
b100 0
b0 /
b11 .
b10 -
b1010 &
$end
#0
$dumpvars
bx :
b0 9
b0 8
b0 7
b0 6
b1001 5
b0 ,
0+
0*
1)
0(
b0 '
0%
b0 $
b0 #
0"
0!
$end
#5000
1(
#10000
0(
#15000
1(
#20000
0(
1*
#25000
1(
#30000
0(
#35000
1(
#40000
0(
b1000000000 '
b1000000000 :
#45000
1%
b1 9
1+
1(
#50000
0(
#55000
b1000000000 $
b1000000000 6
b10 9
0+
1(
#60000
0(
#65000
0)
b1100000000 $
b1100000000 6
b1000 5
b1000000000 8
1(
#70000
0(
#75000
b1010000000 $
b1010000000 6
b111 5
1(
#80000
0(
#85000
b1001000000 $
b1001000000 6
b110 5
1(
#90000
0(
#95000
b1000100000 $
b1000100000 6
b101 5
1(
#100000
0(
#105000
b1000010000 $
b1000010000 6
b100 5
1(
#110000
0(
#115000
b1000001000 $
b1000001000 6
b11 5
1(
#120000
0(
#125000
b1000000100 $
b1000000100 6
b10 5
1(
#130000
0(
#135000
b1000000010 $
b1000000010 6
b1 5
1(
#140000
0(
#145000
b1000000001 $
b1000000001 6
b0 5
1(
#150000
0(
#155000
1)
b1000000000 $
b1000000000 6
b11 9
1(
#160000
0(
#165000
b0 9
0%
1!
1"
b1000000000 #
b1000000000 7
1(
#170000
0(
#175000
0!
0"
1(
#180000
0(
#185000
1(
#190000
0(
#195000
b0 8
b1001 5
1%
b1 9
1+
1(
b1010100101 '
b1010100101 :
#200000
0(
#205000
b10 9
0+
1(
#210000
0(
#215000
0)
b1100000000 $
b1100000000 6
b1000 5
b1000000000 8
1(
#220000
0(
#225000
1)
b1010000000 $
b1010000000 6
b111 5
1(
#230000
0(
#235000
0)
b1011000000 $
b1011000000 6
b110 5
b1010000000 8
1(
#240000
0(
#245000
1)
b1010100000 $
b1010100000 6
b101 5
1(
#250000
0(
#255000
0)
b1010110000 $
b1010110000 6
b100 5
b1010100000 8
1(
#260000
0(
#265000
b1010101000 $
b1010101000 6
b11 5
1(
#270000
0(
#275000
1)
b1010100100 $
b1010100100 6
b10 5
1(
#280000
0(
#285000
0)
b1010100110 $
b1010100110 6
b1 5
b1010100100 8
1(
#290000
0(
#295000
1)
b1010100101 $
b1010100101 6
b0 5
1(
#300000
0(
#305000
b11 9
b1010100101 8
1(
#310000
0(
#315000
b0 9
0%
1!
1"
b1010100101 #
b1010100101 7
1(
#320000
0(
#325000
0!
0"
1(
#330000
0(
#335000
1(
#340000
0(
#345000
b0 8
b1001 5
1%
b1 9
1+
0)
1(
b0 '
b0 :
#350000
0(
#355000
b1000000000 $
b1000000000 6
b10 9
0+
1(
#360000
0(
#365000
b100000000 $
b100000000 6
b1000 5
1(
#370000
0(
#375000
b10000000 $
b10000000 6
b111 5
1(
#380000
0(
#385000
b1000000 $
b1000000 6
b110 5
1(
#390000
0(
#395000
b100000 $
b100000 6
b101 5
1(
#400000
0(
#405000
b10000 $
b10000 6
b100 5
1(
#410000
0(
#415000
b1000 $
b1000 6
b11 5
1(
#420000
0(
#425000
b100 $
b100 6
b10 5
1(
#430000
0(
#435000
b10 $
b10 6
b1 5
1(
#440000
0(
#445000
b1 $
b1 6
b0 5
1(
#450000
0(
#455000
1)
b0 $
b0 6
b11 9
1(
#460000
0(
#465000
b0 9
0%
1!
1"
b0 #
b0 7
1(
#470000
0(
#475000
0!
0"
1(
#480000
0(
#485000
1(
#490000
0(
#495000
b1001 5
1%
b1 9
1+
1(
b1111111111 '
b1111111111 :
#500000
0(
#505000
b1000000000 $
b1000000000 6
b10 9
0+
1(
#510000
0(
#515000
b1100000000 $
b1100000000 6
b1000 5
b1000000000 8
1(
#520000
0(
#525000
b1110000000 $
b1110000000 6
b111 5
b1100000000 8
1(
#530000
0(
#535000
b1111000000 $
b1111000000 6
b110 5
b1110000000 8
1(
#540000
0(
#545000
b1111100000 $
b1111100000 6
b101 5
b1111000000 8
1(
#550000
0(
#555000
b1111110000 $
b1111110000 6
b100 5
b1111100000 8
1(
#560000
0(
#565000
b1111111000 $
b1111111000 6
b11 5
b1111110000 8
1(
#570000
0(
#575000
b1111111100 $
b1111111100 6
b10 5
b1111111000 8
1(
#580000
0(
#585000
b1111111110 $
b1111111110 6
b1 5
b1111111100 8
1(
#590000
0(
#595000
b1111111111 $
b1111111111 6
b0 5
b1111111110 8
1(
#600000
0(
#605000
b11 9
b1111111111 8
1(
#610000
0(
#615000
b0 9
0%
1!
1"
b1111111111 #
b1111111111 7
1(
#620000
0(
#625000
0!
0"
1(
#630000
0(
#635000
1(
#640000
0(
#645000
b0 8
b1001 5
1%
b1 9
1+
0)
1(
b101010 '
b101010 :
#650000
0(
#655000
b1000000000 $
b1000000000 6
b10 9
0+
1(
#660000
0(
#665000
b100000000 $
b100000000 6
b1000 5
1(
#670000
0(
#675000
b10000000 $
b10000000 6
b111 5
1(
#680000
0(
#685000
b1000000 $
b1000000 6
b110 5
1(
#690000
0(
#695000
1)
b100000 $
b100000 6
b101 5
1(
#700000
0(
#705000
0)
b110000 $
b110000 6
b100 5
b100000 8
1(
#710000
0(
#715000
1)
b101000 $
b101000 6
b11 5
1(
#720000
0(
#725000
0)
b101100 $
b101100 6
b10 5
b101000 8
1(
#730000
0(
#735000
1)
b101010 $
b101010 6
b1 5
1(
#740000
0(
#745000
0)
b101011 $
b101011 6
b0 5
b101010 8
1(
#750000
0(
#755000
1)
b101010 $
b101010 6
b11 9
1(
#760000
0(
#765000
b0 9
0%
1!
1"
b101010 #
b101010 7
1(
#770000
0(
#775000
0!
0"
1(
#780000
0(
#785000
1(
#790000
0(
#795000
b0 8
b1001 5
1%
b1 9
1+
1(
b1100001001 '
b1100001001 :
#800000
0(
#805000
b1000000000 $
b1000000000 6
b10 9
0+
1(
#810000
0(
#815000
b1100000000 $
b1100000000 6
b1000 5
b1000000000 8
1(
#820000
0(
#825000
0)
b1110000000 $
b1110000000 6
b111 5
b1100000000 8
1(
#830000
0(
#835000
b1101000000 $
b1101000000 6
b110 5
1(
#840000
0(
#845000
b1100100000 $
b1100100000 6
b101 5
1(
#850000
0(
#855000
b1100010000 $
b1100010000 6
b100 5
1(
#860000
0(
#865000
1)
b1100001000 $
b1100001000 6
b11 5
1(
#870000
0(
#875000
0)
b1100001100 $
b1100001100 6
b10 5
b1100001000 8
1(
#880000
0(
#885000
b1100001010 $
b1100001010 6
b1 5
1(
#890000
0(
#895000
1)
b1100001001 $
b1100001001 6
b0 5
1(
#900000
0(
#905000
b11 9
b1100001001 8
1(
#910000
0(
#915000
b0 9
0%
1!
1"
b1100001001 #
b1100001001 7
1(
#920000
0(
#925000
0!
0"
1(
#930000
0(
#935000
1(
#940000
0(
#945000
b0 8
b1001 5
1%
b1 9
1+
0)
1(
b111 '
b111 :
#950000
0(
#955000
b1000000000 $
b1000000000 6
b10 9
0+
1(
#960000
0(
#965000
b100000000 $
b100000000 6
b1000 5
1(
#970000
0(
#975000
b10000000 $
b10000000 6
b111 5
1(
#980000
0(
#985000
b1000000 $
b1000000 6
b110 5
1(
#990000
0(
#995000
b100000 $
b100000 6
b101 5
1(
#1000000
0(
#1005000
b10000 $
b10000 6
b100 5
1(
#1010000
0(
#1015000
b1000 $
b1000 6
b11 5
1(
#1020000
0(
#1025000
1)
b100 $
b100 6
b10 5
1(
#1030000
0(
#1035000
b110 $
b110 6
b1 5
b100 8
1(
#1040000
0(
#1045000
b111 $
b111 6
b0 5
b110 8
1(
#1050000
0(
#1055000
b11 9
b111 8
1(
#1060000
0(
#1065000
b0 9
0%
1!
1"
b111 #
b111 7
1(
#1070000
0(
#1075000
0!
0"
1(
