designs/rtl/sar_logic/sar_logic.v
module sar_logic #(
    parameter N = 8
)(
    input  wire         clk,
    input  wire         rst_n,
    input  wire         start,
    output reg          eoc,
    output reg          busy,
    input  wire         comp_out,
    output reg [N-1:0]  dac_out,
    output reg [N-1:0]  dout,
    output reg          dout_valid
);

localparam IDLE    = 2'd0;
localparam SAMPLE  = 2'd1;
localparam CONVERT = 2'd2;
localparam DONE    = 2'd3;

reg [1:0]          state;
reg [$clog2(N)-1:0]  bit_idx;    // 
reg [N-1:0]        sar_reg;

always @(posedge clk or negedge rst_n) begin
    if (!rst_n) begin
        state      <= IDLE;
        dac_out    <= {N{1'b0}};
        dout       <= {N{1'b0}};
        dout_valid <= 1'b0;
        busy       <= 1'b0;
        eoc        <= 1'b0;
        bit_idx    <= N - 1;
        sar_reg    <= {N{1'b0}};
    end
    else begin
        dout_valid <= 1'b0;
        eoc        <= 1'b0;

        case (state)

            IDLE: begin
                busy <= 1'b0;
                if (start) begin
                    state   <= SAMPLE;
                    busy    <= 1'b1;
                    bit_idx <= N - 1;
                    sar_reg <= {N{1'b0}};
                end
            end

            SAMPLE: begin
                state   <= CONVERT;
                dac_out <= ({N{1'b0}} | (1 << (N-1)));
            end

            CONVERT: begin
                // Capture comparator result for current bit
                if (comp_out)
                    sar_reg <= sar_reg | ({N{1'b0}} | (1 << bit_idx));

                if (bit_idx == 0) begin
                    state   <= DONE;
                    // ✅ Bug 2 fixed: update dac_out on final bit too
                    dac_out <= (sar_reg | ({N{1'b0}} | (comp_out << bit_idx)));
                end
                else begin
                    bit_idx <= bit_idx - 1;
                    dac_out <= (sar_reg | ({N{1'b0}} | (comp_out << bit_idx)))
                             | ({N{1'b0}} | (1 << (bit_idx - 1)));
                end
            end

            DONE: begin
                dout       <= sar_reg;
                dout_valid <= 1'b1;
                eoc        <= 1'b1;
                busy       <= 1'b0;
                state      <= IDLE;
            end

        endcase
    end
end

endmodule

designs/rtl/sar_logic/tb_sar_logic.v
`timescale 1ns/1ps

module tb_sar_logic;
    parameter N = 8;

    // Testbench signals
    reg            clk;
    reg            rst_n;
    reg            start;
    reg            comp_out;
    wire [N-1:0]   dac_out;
    wire [N-1:0]   dout;
    wire           dout_valid;
    wire           busy;
    wire           eoc;

    // Internal testbench variables
    reg  [N-1:0]   Vin;
    integer        errors;

    // Instantiate DUT
    sar_logic #(.N(N)) dut (
        .clk(clk),
        .rst_n(rst_n),
        .start(start),
        .comp_out(comp_out),
        .dac_out(dac_out),
        .dout(dout),
        .dout_valid(dout_valid),
        .busy(busy),
        .eoc(eoc)
    );

    // Clock generation: 10ns period (100 MHz)
    initial begin
        clk = 0;
        forever #5 clk = ~clk;
    end

    // Mock Comparator: compares DAC output against the analog input (Vin)
    always @(*) begin
        comp_out = (dac_out <= Vin);
    end

    // VCD Dump for GTKWave
    initial begin
        $dumpfile("sar_sim.vcd");
        $dumpvars(0, tb_sar_logic);
    end

    // Watchdog Timer (prevents simulation from hanging if 'eoc' never asserts)
    initial begin
        #5000;
        $display("\n[FATAL ERROR] Simulation Timeout! EOC never asserted.");
        $finish;
    end

    // Reusable task to test a specific voltage value
    task test_voltage;
        input [N-1:0] test_val;
        begin
            Vin = test_val;
            
            // Trigger conversion
            @(posedge clk);
            start = 1;
            @(posedge clk);
            start = 0;

            // Wait for End of Conversion
            wait(eoc);
            
            // Check results on the next clock cycle when dout_valid should be high
            @(posedge clk);
            if (dout === Vin && dout_valid === 1'b1) begin
                $display("[PASS] Vin = %3d (0x%h) | ADC out = %3d", Vin, Vin, dout);
            end else begin
                $display("[FAIL] Vin = %3d (0x%h) | Expected = %3d, Got = %3d, Valid = %b", 
                         Vin, Vin, Vin, dout, dout_valid);
                errors = errors + 1;
            end
            
            // Small delay between conversions
            #20;
        end
    endtask

    // Main Stimulus Sequence
    initial begin
        // Initialize
        rst_n = 0;
        start = 0;
        Vin   = 0;
        errors = 0;

        // Apply Reset
        #20;
        rst_n = 1;
        #20;

        $display("========================================");
        $display("   Starting SAR ADC Testbench   ");
        $display("========================================");

        // Test Case 1: Mid-scale
        test_voltage(8'd128);

        // Test Case 2: User's original test
        test_voltage(8'hA5);

        // Test Case 3: Zero scale (Edge Case)
        test_voltage(8'd0);

        // Test Case 4: Full scale (Edge Case)
        test_voltage(8'd255);

        // Test Case 5: Random values
        test_voltage(8'd42);
        test_voltage(8'd199);
        test_voltage(8'd7);

        // Final Report
        $display("========================================");
        if (errors == 0)
            $display("   SIMULATION PASSED! (0 Errors)   ");
        else
            $display("   SIMULATION FAILED! (%0d Errors)   ", errors);
        $display("========================================");
        
        $finish;
    end
endmodule

designs/rtl/sar_logic/sar_sim.vcd
$date
	Mon Jun 29 16:44:41 2026
$end
$version
	Icarus Verilog
$end
$timescale
	1ps
$end
$scope module tb_sar_logic $end
$var wire 1 ! eoc $end
$var wire 1 " dout_valid $end
$var wire 8 # dout [7:0] $end
$var wire 8 $ dac_out [7:0] $end
$var wire 1 % busy $end
$var parameter 32 & N $end
$var reg 8 ' Vin [7:0] $end
$var reg 1 ( clk $end
$var reg 1 ) comp_out $end
$var reg 1 * rst_n $end
$var reg 1 + start $end
$var integer 32 , errors [31:0] $end
$scope module dut $end
$var wire 1 ( clk $end
$var wire 1 ) comp_out $end
$var wire 1 * rst_n $end
$var wire 1 + start $end
$var parameter 2 - CONVERT $end
$var parameter 2 . DONE $end
$var parameter 2 / IDLE $end
$var parameter 32 0 N $end
$var parameter 2 1 SAMPLE $end
$var reg 3 2 bit_idx [2:0] $end
$var reg 1 % busy $end
$var reg 8 3 dac_out [7:0] $end
$var reg 8 4 dout [7:0] $end
$var reg 1 " dout_valid $end
$var reg 1 ! eoc $end
$var reg 8 5 sar_reg [7:0] $end
$var reg 2 6 state [1:0] $end
$upscope $end
$scope task test_voltage $end
$var reg 8 7 test_val [7:0] $end
$upscope $end
$upscope $end
$enddefinitions $end
$comment Show the parameter values. $end
$dumpall
b1 1
b1000 0
b0 /
b11 .
b10 -
b1000 &
$end
#0
$dumpvars
bx 7
b0 6
b0 5
b0 4
b0 3
b111 2
b0 ,
0+
0*
1)
0(
b0 '
0%
b0 $
b0 #
0"
0!
$end
#5000
1(
#10000
0(
#15000
1(
#20000
0(
1*
#25000
1(
#30000
0(
#35000
1(
#40000
0(
b10000000 '
b10000000 7
#45000
1%
b1 6
1+
1(
#50000
0(
#55000
b10000000 $
b10000000 3
b10 6
0+
1(
#60000
0(
#65000
0)
b11000000 $
b11000000 3
b110 2
b10000000 5
1(
#70000
0(
#75000
b10100000 $
b10100000 3
b101 2
1(
#80000
0(
#85000
b10010000 $
b10010000 3
b100 2
1(
#90000
0(
#95000
b10001000 $
b10001000 3
b11 2
1(
#100000
0(
#105000
b10000100 $
b10000100 3
b10 2
1(
#110000
0(
#115000
b10000010 $
b10000010 3
b1 2
1(
#120000
0(
#125000
b10000001 $
b10000001 3
b0 2
1(
#130000
0(
#135000
1)
b10000000 $
b10000000 3
b11 6
1(
#140000
0(
#145000
b0 6
0%
1!
1"
b10000000 #
b10000000 4
1(
#150000
0(
#155000
0!
0"
1(
#160000
0(
#165000
1(
#170000
0(
#175000
b0 5
b111 2
1%
b1 6
1+
1(
b10100101 '
b10100101 7
#180000
0(
#185000
b10 6
0+
1(
#190000
0(
#195000
0)
b11000000 $
b11000000 3
b110 2
b10000000 5
1(
#200000
0(
#205000
1)
b10100000 $
b10100000 3
b101 2
1(
#210000
0(
#215000
0)
b10110000 $
b10110000 3
b100 2
b10100000 5
1(
#220000
0(
#225000
b10101000 $
b10101000 3
b11 2
1(
#230000
0(
#235000
1)
b10100100 $
b10100100 3
b10 2
1(
#240000
0(
#245000
0)
b10100110 $
b10100110 3
b1 2
b10100100 5
1(
#250000
0(
#255000
1)
b10100101 $
b10100101 3
b0 2
1(
#260000
0(
#265000
b11 6
b10100101 5
1(
#270000
0(
#275000
b0 6
0%
1!
1"
b10100101 #
b10100101 4
1(
#280000
0(
#285000
0!
0"
1(
#290000
0(
#295000
1(
#300000
0(
#305000
b0 5
b111 2
1%
b1 6
1+
0)
1(
b0 '
b0 7
#310000
0(
#315000
b10000000 $
b10000000 3
b10 6
0+
1(
#320000
0(
#325000
b1000000 $
b1000000 3
b110 2
1(
#330000
0(
#335000
b100000 $
b100000 3
b101 2
1(
#340000
0(
#345000
b10000 $
b10000 3
b100 2
1(
#350000
0(
#355000
b1000 $
b1000 3
b11 2
1(
#360000
0(
#365000
b100 $
b100 3
b10 2
1(
#370000
0(
#375000
b10 $
b10 3
b1 2
1(
#380000
0(
#385000
b1 $
b1 3
b0 2
1(
#390000
0(
#395000
1)
b0 $
b0 3
b11 6
1(
#400000
0(
#405000
b0 6
0%
1!
1"
b0 #
b0 4
1(
#410000
0(
#415000
0!
0"
1(
#420000
0(
#425000
1(
#430000
0(
#435000
b111 2
1%
b1 6
1+
1(
b11111111 '
b11111111 7
#440000
0(
#445000
b10000000 $
b10000000 3
b10 6
0+
1(
#450000
0(
#455000
b11000000 $
b11000000 3
b110 2
b10000000 5
1(
#460000
0(
#465000
b11100000 $
b11100000 3
b101 2
b11000000 5
1(
#470000
0(
#475000
b11110000 $
b11110000 3
b100 2
b11100000 5
1(
#480000
0(
#485000
b11111000 $
b11111000 3
b11 2
b11110000 5
1(
#490000
0(
#495000
b11111100 $
b11111100 3
b10 2
b11111000 5
1(
#500000
0(
#505000
b11111110 $
b11111110 3
b1 2
b11111100 5
1(
#510000
0(
#515000
b11111111 $
b11111111 3
b0 2
b11111110 5
1(
#520000
0(
#525000
b11 6
b11111111 5
1(
#530000
0(
#535000
b0 6
0%
1!
1"
b11111111 #
b11111111 4
1(
#540000
0(
#545000
0!
0"
1(
#550000
0(
#555000
1(
#560000
0(
#565000
b0 5
b111 2
1%
b1 6
1+
0)
1(
b101010 '
b101010 7
#570000
0(
#575000
b10000000 $
b10000000 3
b10 6
0+
1(
#580000
0(
#585000
b1000000 $
b1000000 3
b110 2
1(
#590000
0(
#595000
1)
b100000 $
b100000 3
b101 2
1(
#600000
0(
#605000
0)
b110000 $
b110000 3
b100 2
b100000 5
1(
#610000
0(
#615000
1)
b101000 $
b101000 3
b11 2
1(
#620000
0(
#625000
0)
b101100 $
b101100 3
b10 2
b101000 5
1(
#630000
0(
#635000
1)
b101010 $
b101010 3
b1 2
1(
#640000
0(
#645000
0)
b101011 $
b101011 3
b0 2
b101010 5
1(
#650000
0(
#655000
1)
b101010 $
b101010 3
b11 6
1(
#660000
0(
#665000
b0 6
0%
1!
1"
b101010 #
b101010 4
1(
#670000
0(
#675000
0!
0"
1(
#680000
0(
#685000
1(
#690000
0(
#695000
b0 5
b111 2
1%
b1 6
1+
1(
b11000111 '
b11000111 7
#700000
0(
#705000
b10000000 $
b10000000 3
b10 6
0+
1(
#710000
0(
#715000
b11000000 $
b11000000 3
b110 2
b10000000 5
1(
#720000
0(
#725000
0)
b11100000 $
b11100000 3
b101 2
b11000000 5
1(
#730000
0(
#735000
b11010000 $
b11010000 3
b100 2
1(
#740000
0(
#745000
b11001000 $
b11001000 3
b11 2
1(
#750000
0(
#755000
1)
b11000100 $
b11000100 3
b10 2
1(
#760000
0(
#765000
b11000110 $
b11000110 3
b1 2
b11000100 5
1(
#770000
0(
#775000
b11000111 $
b11000111 3
b0 2
b11000110 5
1(
#780000
0(
#785000
b11 6
b11000111 5
1(
#790000
0(
#795000
b0 6
0%
1!
1"
b11000111 #
b11000111 4
1(
#800000
0(
#805000
0!
0"
1(
#810000
0(
#815000
1(
#820000
0(
#825000
b0 5
b111 2
1%
b1 6
1+
0)
1(
b111 '
b111 7
#830000
0(
#835000
b10000000 $
b10000000 3
b10 6
0+
1(
#840000
0(
#845000
b1000000 $
b1000000 3
b110 2
1(
#850000
0(
#855000
b100000 $
b100000 3
b101 2
1(
#860000
0(
#865000
b10000 $
b10000 3
b100 2
1(
#870000
0(
#875000
b1000 $
b1000 3
b11 2
1(
#880000
0(
#885000
1)
b100 $
b100 3
b10 2
1(
#890000
0(
#895000
b110 $
b110 3
b1 2
b100 5
1(
#900000
0(
#905000
b111 $
b111 3
b0 2
b110 5
1(
#910000
0(
#915000
b11 6
b111 5
1(
#920000
0(
#925000
b0 6
0%
1!
1"
b111 #
b111 4
1(
#930000
0(
#935000
0!
0"
1(
